setup.py
xpm.py
xpm.egg-info/PKG-INFO
xpm.egg-info/SOURCES.txt
xpm.egg-info/dependency_links.txt
xpm.egg-info/top_level.txt