Metadata-Version: 1.1
Name: xpm
Version: 0.0.4
Summary: Library to output XPM files
Home-page: https://github.com/talwrii/nm-noauto
Author: Tal Wrii
Author-email: talwrii@gmail.com
License: BSD
Keywords: xpm image PIL graphics
Platform: UNKNOWN
Classifier: Development Status :: 3 - Alpha
Classifier: Topic :: Multimedia :: Graphics
Classifier: License :: OSI Approved :: BSD License
